polymo/__init__.py
polymo/builder/__init__.py
polymo/builder/app.py
polymo/builder/static/examples/countries.yml
polymo/builder/static/examples/githubrepos.yml
polymo/builder/static/examples/jsonplaceholder.yml
polymo/builder/static/examples/jsonplaceholder_endpoints.yml
polymo/builder/static/examples/multi_endpoints.yml
polymo/builder/static/examples/weather.yml
polymo/builder/static/favicon.ico
polymo/builder/static/favicon.png
polymo/builder/static/index.html
polymo/builder/static/logo.png
polymo/builder/static/logo192.png
polymo/builder/static/main.css
polymo/builder/static/main.js
polymo/builder/static/mockServiceWorker.js
polymo/builder/templates/index.html
polymo/cli.py
polymo/config.py
polymo/datasource.py
polymo/py.typed
polymo/pydantic_config.py
polymo/rest_client.py
polymo/scripts/__init__.py
polymo/scripts/smoke.py
polymo-0.9.1.dist-info/WHEEL
polymo-0.9.1.dist-info/entry_points.txt
polymo-0.9.1.dist-info/METADATA
polymo-0.9.1.dist-info/RECORD
