Metadata-Version: 2.3
Name: polymo
Version: 0.9.1
Summary: Declarative REST API ingestion for PySpark
Keywords: spark,pyspark,rest,api,ingestion,data-engineering,etl,http
Author: Daniel Tom
Author-email: Daniel Tom <d.e.tom89@gmail.com>
License: BSD-3
Classifier: Development Status :: 4 - Beta
Classifier: Intended Audience :: Developers
Classifier: Intended Audience :: Information Technology
Classifier: Topic :: Internet :: WWW/HTTP
Classifier: Topic :: Software Development :: Libraries
Classifier: Topic :: Database
Classifier: License :: OSI Approved :: MIT License
Classifier: Programming Language :: Python :: 3
Classifier: Programming Language :: Python :: 3.10
Classifier: Programming Language :: Python :: 3.11
Classifier: Programming Language :: Python :: 3.12
Classifier: Programming Language :: Python :: 3.13
Classifier: Operating System :: OS Independent
Classifier: Typing :: Typed
Requires-Dist: fsspec>=2025.9.0
Requires-Dist: httpx>=0.26
Requires-Dist: jinja2>=3.1.6
Requires-Dist: pyyaml>=6.0.1
Requires-Dist: pyspark>=4 ; extra == 'benchmark'
Requires-Dist: pyarrow>=13 ; extra == 'benchmark'
Requires-Dist: httpx>=0.26 ; extra == 'benchmark'
Requires-Dist: notebook>=7.4.7 ; extra == 'benchmark'
Requires-Dist: fastapi>=0.110 ; extra == 'benchmark'
Requires-Dist: uvicorn>=0.24 ; extra == 'benchmark'
Requires-Dist: fastapi>=0.110 ; extra == 'builder'
Requires-Dist: uvicorn>=0.24 ; extra == 'builder'
Requires-Dist: jinja2>=3.1.6 ; extra == 'builder'
Requires-Dist: pyspark>=4 ; extra == 'builder'
Requires-Dist: pyarrow>=13 ; extra == 'builder'
Requires-Dist: pyspark>=4 ; extra == 'smoke'
Requires-Dist: pyarrow>=13 ; extra == 'smoke'
Requires-Python: >=3.10
Project-URL: Documentation, https://dan1elt0m.github.io/polymo/
Project-URL: Homepage, https://github.com/dan1elt0m/polymo
Project-URL: Issues, https://github.com/dan1elt0m/polymo/issues
Project-URL: Repository, https://github.com/dan1elt0m/polymo.git
Provides-Extra: benchmark
Provides-Extra: builder
Provides-Extra: smoke
